<keymap version="1" name="Default copy" parent="$default">
  <action id="ActivateLogcatToolWindow">
    <keyboard-shortcut first-keystroke="alt 6" />
  </action>
  <action id="ActivateTODOToolWindow" />
  <action id="Back">
    <mouse-shortcut keystroke="button4" />
    <keyboard-shortcut first-keystroke="ctrl alt page_up" />
    <keyboard-shortcut first-keystroke="alt comma" />
  </action>
  <action id="Debugger.EditTypeSource" />
  <action id="EditSource" />
  <action id="EditSourceInNewWindow" />
  <action id="FindInPath">
    <keyboard-shortcut first-keystroke="shift ctrl f" />
    <keyboard-shortcut first-keystroke="f10" />
  </action>
  <action id="FindNext">
    <keyboard-shortcut first-keystroke="ctrl l" />
    <keyboard-shortcut first-keystroke="f4" />
  </action>
  <action id="FindPrevious">
    <keyboard-shortcut first-keystroke="shift ctrl l" />
    <keyboard-shortcut first-keystroke="f3" />
  </action>
  <action id="Forward">
    <keyboard-shortcut first-keystroke="ctrl alt right" />
    <mouse-shortcut keystroke="button5" />
    <keyboard-shortcut first-keystroke="ctrl alt page_down" />
    <keyboard-shortcut first-keystroke="alt period" />
  </action>
  <action id="SurroundWith">
    <keyboard-shortcut first-keystroke="ctrl alt t" />
    <keyboard-shortcut first-keystroke="alt t" />
  </action>
  <action id="UpdateRunningApplication" />
  <action id="Vcs.EditSource" />
  <action id="XDebugger.JumpToSource" />
  <action id="android.deploy.ApplyChanges">
    <keyboard-shortcut first-keystroke="ctrl f10" />
  </action>
  <action id="android.deploy.CodeSwap">
    <keyboard-shortcut first-keystroke="ctrl alt f10" />
  </action>
</keymap>